{
  "type": "FeatureCollection",
  "features": [
    
    {
      "type": "Feature",
      "geometry": {
        "type": "Polygon",
        "coordinates": [
          [
            [
              105.28573885560036,
              -5.438031757554418
            ],
            [
              105.28453722596169,
              -5.43768997990371
            ],
            [
              105.2829922735691,
              -5.437348202058911
            ],
            [
              105.28024569153786,
              -5.4367928126472345
            ],
            [
              105.27865782380104,
              -5.43662192349441
            ],
            [
              105.2780570089817,
              -5.436920979480035
            ],
            [
              105.27706995606422,
              -5.437647257683707
            ],
            [
              105.27608290314674,
              -5.437305479814661
            ],
            [
              105.27483835816383,
              -5.4363228673602295
            ],
            [
              105.27432337403297,
              -5.436493756597948
            ],
            [
              105.27428045868874,
              -5.436920979480035
            ],
            [
              105.27325049042702,
              -5.436963701751561
            ],
            [
              105.27350798249245,
              -5.436194700400105
            ],
            [
              105.27282133698463,
              -5.436066533412692
            ],
            [
              105.27204886078835,
              -5.43662192349441
            ],
            [
              105.2713192999363,
              -5.43628014504322
            ],
            [
              105.2720059454441,
              -5.435724754646233
            ],
            [
              105.27119055390358,
              -5.435254808525566
            ],
            [
              105.27067556977272,
              -5.4358101993560375
            ],
            [
              105.27011767029762,
              -5.435425698066431
            ],
            [
              105.27058973908424,
              -5.434784862038156
            ],
            [
              105.2698601782322,
              -5.434272192724542
            ],
            [
              105.27063265442848,
              -5.433503187935912
            ],
            [
              105.27007475495338,
              -5.43269145959394
            ],
            [
              105.27037516236305,
              -5.431965175413533
            ],
            [
              105.27024641633034,
              -5.431281613032267
            ],
            [
              105.26883020997047,
              -5.431238890357687
            ],
            [
              105.26878729462624,
              -5.4297435948395325
            ],
            [
              105.26861563324928,
              -5.428162849829939
            ],
            [
              105.26788607239723,
              -5.428034681133996
            ],
            [
              105.26792898774147,
              -5.427479283136794
            ],
            [
              105.267843157053,
              -5.427009330585796
            ],
            [
              105.26290789246559,
              -5.426582100676199
            ],
            [
              105.26247873902321,
              -5.425642193809848
            ],
            [
              105.2588738501072,
              -5.426154870463952
            ],
            [
              105.25919705629349,
              -5.42794923532157
            ],
            [
              105.25971204042435,
              -5.429829040397654
            ],
            [
              105.25816708803177,
              -5.4297435948395325
            ],
            [
              105.25782376527786,
              -5.428547355754275
            ],
            [
              105.25593549013138,
              -5.429060029938616
            ],
            [
              105.25456219911575,
              -5.428120126934311
            ],
            [
              105.25233060121536,
              -5.428034681133996
            ],
            [
              105.25207310914993,
              -5.423847822089535
            ],
            [
              105.25052815675735,
              -5.423676929266439
            ],
            [
              105.24898320436478,
              -5.425044070496029
            ],
            [
              105.24700909852982,
              -5.425556747658463
            ],
            [
              105.24520665407181,
              -5.4257276399491206
            ],
            [
              105.24246007204056,
              -5.425300409131716
            ],
            [
              105.24160176515579,
              -5.4241896075905265
            ],
            [
              105.2404859662056,
              -5.42589853219137
            ],
            [
              105.23876935243607,
              -5.42624031653062
            ],
            [
              105.23954182863235,
              -5.428205572722527
            ],
            [
              105.2382543683052,
              -5.4296581492693115
            ],
            [
              105.23619443178177,
              -5.429914485943652
            ],
            [
              105.23542195558548,
              -5.431708839611429
            ],
            [
              105.23396283388138,
              -5.432648737019331
            ],
            [
              105.23250371217728,
              -5.432734182165521
            ],
            [
              105.2313020825386,
              -5.431708839611429
            ],
            [
              105.23010045289993,
              -5.432136065887687
            ],
            [
              105.22967129945755,
              -5.433246852788187
            ],
            [
              105.22872716188431,
              -5.432221511106585
            ],
            [
              105.22718220949173,
              -5.431196167680079
            ],
            [
              105.22606641054153,
              -5.432221511106585
            ],
            [
              105.22503644227982,
              -5.431794284890909
            ],
            [
              105.22392064332962,
              -5.431708839611429
            ],
            [
              105.22366315126419,
              -5.430427158965296
            ],
            [
              105.2217748761177,
              -5.4296581492693115
            ],
            [
              105.22022992372513,
              -5.428803692900941
            ],
            [
              105.21765500307083,
              -5.429230921236508
            ],
            [
              105.21465092897415,
              -5.428120126934311
            ],
            [
              105.21267682313919,
              -5.428034681133996
            ],
            [
              105.20993024110794,
              -5.427522006077827
            ],
            [
              105.20907193422318,
              -5.428632801481934
            ],
            [
              105.20718365907669,
              -5.428291018498618
            ],
            [
              105.20486623048782,
              -5.430683495312587
            ],
            [
              105.20254880189896,
              -5.431794284890909
            ],
            [
              105.20357877016068,
              -5.434186747796514
            ],
            [
              105.20409375429153,
              -5.436664645787158
            ],
            [
              105.20272046327591,
              -5.438031757554418
            ],
            [
              105.20108968019485,
              -5.439398866216323
            ],
            [
              105.20340710878372,
              -5.442731180565231
            ],
            [
              105.20340710878372,
              -5.44572170336171
            ],
            [
              105.20572453737259,
              -5.445892589929264
            ],
            [
              105.20778447389603,
              -5.444098278546618
            ],
            [
              105.21035939455032,
              -5.445807146651562
            ],
            [
              105.21104604005814,
              -5.447430566850663
            ],
            [
              105.21310597658157,
              -5.446832465182315
            ],
            [
              105.21576672792435,
              -5.4462343629186405
            ],
            [
              105.21576672792435,
              -5.445209043367465
            ],
            [
              105.21765500307083,
              -5.4443546090720565
            ],
            [
              105.22014409303665,
              -5.444098278546618
            ],
            [
              105.22134572267532,
              -5.442389405584231
            ],
            [
              105.22280484437943,
              -5.440253307552743
            ],
            [
              105.22486478090286,
              -5.439398866216323
            ],
            [
              105.22572308778763,
              -5.437091868547976
            ],
            [
              105.22761136293411,
              -5.438202646307001
            ],
            [
              105.2283838391304,
              -5.4397406428965045
            ],
            [
              105.22967129945755,
              -5.439227977803437
            ],
            [
              105.22975713014603,
              -5.436579201198622
            ],
            [
              105.23078709840775,
              -5.437775424334579
            ],
            [
              105.23164540529251,
              -5.437860868753312
            ],
            [
              105.23181706666946,
              -5.436151978073999
            ],
            [
              105.23267537355423,
              -5.435639309924304
            ],
            [
              105.23396283388138,
              -5.435724754646233
            ],
            [
              105.23404866456985,
              -5.437177313063741
            ],
            [
              105.23585110902786,
              -5.436920979480035
            ],
            [
              105.23576527833939,
              -5.435468420444061
            ],
            [
              105.23731023073196,
              -5.434699417182847
            ],
            [
              105.24014264345169,
              -5.43461397231544
            ],
            [
              105.23945599794388,
              -5.435468420444061
            ],
            [
              105.23954182863235,
              -5.436408311985151
            ],
            [
              105.24349004030228,
              -5.435041196531297
            ],
            [
              105.24400502443314,
              -5.436920979480035
            ],
            [
              105.246322453022,
              -5.436493756597948
            ],
            [
              105.24629965424538,
              -5.437476368773444
            ],
            [
              105.24552717804909,
              -5.438117201936777
            ],
            [
              105.24599924683571,
              -5.440039697332397
            ],
            [
              105.2471150457859,
              -5.439398866216323
            ],
            [
              105.2471150457859,
              -5.437604535460702
            ],
            [
              105.24938955903053,
              -5.439655198744659
            ],
            [
              105.25067701935768,
              -5.438458979344886
            ],
            [
              105.25140658020973,
              -5.438159924123396
            ],
            [
              105.2520503103733,
              -5.438373535011048
            ],
            [
              105.25290861725807,
              -5.440082419382532
            ],
            [
              105.25243654847145,
              -5.440381473648544
            ],
            [
              105.25299444794655,
              -5.44110774767564
            ],
            [
              105.25449648499489,
              -5.441022303717961
            ],
            [
              105.25878801941872,
              -5.439270699911203
            ],
            [
              105.26140585541725,
              -5.439356144117653
            ],
            [
              105.26119127869606,
              -5.441492245334987
            ],
            [
              105.26136294007301,
              -5.443030233514265
            ],
            [
              105.26080504059792,
              -5.4443546090720565
            ],
            [
              105.26093378663063,
              -5.445465373419242
            ],
            [
              105.26320829987526,
              -5.445337208407017
            ],
            [
              105.26479616761208,
              -5.445251765050348
            ],
            [
              105.26548281311989,
              -5.445038156605554
            ],
            [
              105.26895895600319,
              -5.44392739146894
            ],
            [
              105.26973143219948,
              -5.443799226128815
            ],
            [
              105.27071848511696,
              -5.443500173562248
            ],
            [
              105.27161970734596,
              -5.444269165575723
            ],
            [
              105.2722205221653,
              -5.445166321681542
            ],
            [
              105.27234926819801,
              -5.446191641305603
            ],
            [
              105.27325049042702,
              -5.446063476448258
            ],
            [
              105.27376547455788,
              -5.444226443823007
            ],
            [
              105.27398005127907,
              -5.442902067982898
            ],
            [
              105.27539625763893,
              -5.439356144117653
            ],
            [
              105.27689829468727,
              -5.43995425322303
            ],
            [
              105.27689829468727,
              -5.440253307552743
            ],
            [
              105.27732744812965,
              -5.440296029587714
            ],
            [
              105.27809992432594,
              -5.439911531163785
            ],
            [
              105.27896828949451,
              -5.439826087036214
            ],
            [
              105.27946181595325,
              -5.440082419382532
            ],
            [
              105.279955342412,
              -5.440765971772113
            ],
            [
              105.28008408844471,
              -5.440253307552743
            ],
            [
              105.28158612549305,
              -5.440231946534119
            ],
            [
              105.28304524719715,
              -5.4401678634737065
            ],
            [
              105.28405375778675,
              -5.439804726002425
            ],
            [
              105.28456874191761,
              -5.439462949358655
            ],
            [
              105.28482623398304,
              -5.4385444236665865
            ],
            [
              105.28525538742542,
              -5.438074479747118
            ],
            [
              105.28573885560036,
              -5.438031757554418
            ]
          ]
        ]
      },
      "properties": {}
    }
  ]
}